{
  "issue": "이란 전쟁",
  "collected_at": "2026-04-03 23:19 UTC",
  "news_count": 20,
  "articles": [
    {
      "title": "Iran war: What is happening on day 35 of US-Israeli attacks? - Al Jazeera",
      "source": "Google News Iran",
      "published_at": "2026-04-03 18:53:30",
      "summary": "Iran war: What is happening on day 35 of US-Israeli attacks? Al Jazeera"
    },
    {
      "title": "Opinion | Trump Has Lost Control of the Iran War - The New York Times",
      "source": "Google News Iran",
      "published_at": "2026-04-03 15:00:18",
      "summary": "Opinion | Trump Has Lost Control of the Iran War The New York Times"
    },
    {
      "title": "French-Owned Container Ship Exits Hormuz in First Since Iran War - bloomberg.com",
      "source": "Google News Iran",
      "published_at": "2026-04-03 20:44:51",
      "summary": "French-Owned Container Ship Exits Hormuz in First Since Iran War bloomberg.com"
    },
    {
      "title": "Trump says war in Iran will not end until Strait of Hormuz is reopened - Politico",
      "source": "Google News Iran",
      "published_at": "2026-04-01 16:33:00",
      "summary": "Trump says war in Iran will not end until Strait of Hormuz is reopened Politico"
    },
    {
      "title": "White House: Reopening Strait of Hormuz Not Vital to Ending Iran War - Time Magazine",
      "source": "Google News Iran",
      "published_at": "2026-03-31 19:24:07",
      "summary": "White House: Reopening Strait of Hormuz Not Vital to Ending Iran War Time Magazine"
    },
    {
      "title": "First Western shipping vessel transits Strait of Hormuz since start of war - upi.com",
      "source": "Google News Iran",
      "published_at": "2026-04-03 20:51:19",
      "summary": "First Western shipping vessel transits Strait of Hormuz since start of war upi.com"
    },
    {
      "title": "Taking Stock of the War in Iran - cfr.org",
      "source": "Google News Iran",
      "published_at": "2026-04-03 17:48:09",
      "summary": "Taking Stock of the War in Iran cfr.org"
    },
    {
      "title": "Exclusive: US intelligence warns Iran unlikely to ease Hormuz Strait chokehold soon, sources say - Reuters",
      "source": "Google News Iran",
      "published_at": "2026-04-03 21:45:32",
      "summary": "Exclusive: US intelligence warns Iran unlikely to ease Hormuz Strait chokehold soon, sources say Reuters"
    },
    {
      "title": "Live updates: US fighter jet reportedly shot down over Iran - NewsNation",
      "source": "Google News Iran",
      "published_at": "2026-04-03 21:46:59",
      "summary": "Live updates: US fighter jet reportedly shot down over Iran NewsNation"
    },
    {
      "title": "Opinion | Trump’s Iran own goal - The Washington Post",
      "source": "Google News Iran",
      "published_at": "2026-04-03 18:45:40",
      "summary": "Opinion | Trump’s Iran own goal The Washington Post"
    },
    {
      "title": "Trump attacks allies, signals Iran war may end without opening Hormuz - Axios",
      "source": "Google News Iran",
      "published_at": "2026-03-31 20:19:04",
      "summary": "Trump attacks allies, signals Iran war may end without opening Hormuz Axios"
    },
    {
      "title": "France sends first Western European ship through Hormuz - Euronews.com",
      "source": "Google News Iran",
      "published_at": "2026-04-03 09:29:37",
      "summary": "France sends first Western European ship through Hormuz Euronews.com"
    },
    {
      "title": "World anxious to open Hormuz Strait while Trump and Iran trade threats - Reuters",
      "source": "Google News Iran",
      "published_at": "2026-04-02 04:23:00",
      "summary": "World anxious to open Hormuz Strait while Trump and Iran trade threats Reuters"
    },
    {
      "title": "UK and allies discuss sanctions to stop Iran blocking Strait of Hormuz - BBC",
      "source": "Google News Iran",
      "published_at": "2026-04-02 17:15:56",
      "summary": "UK and allies discuss sanctions to stop Iran blocking Strait of Hormuz BBC"
    },
    {
      "title": "As Trump doubles down on Iran war, markets shudder and oil prices climb - The Washington Post",
      "source": "Google News Iran",
      "published_at": "2026-04-03 05:11:12",
      "summary": "As Trump doubles down on Iran war, markets shudder and oil prices climb The Washington Post"
    },
    {
      "title": "Iran and Oman drafting protocol to 'monitor' Hormuz Strait traffic: IRNA - CNBC",
      "source": "Google News Iran",
      "published_at": "2026-04-02 15:01:43",
      "summary": "Iran and Oman drafting protocol to 'monitor' Hormuz Strait traffic: IRNA CNBC"
    },
    {
      "title": "As Iran war rages on and oil prices rise, Trump says U.S. \"hasn't even started destroying what's left\" - CBS News",
      "source": "Google News Iran",
      "published_at": "2026-04-02 09:35:00",
      "summary": "As Iran war rages on and oil prices rise, Trump says U.S. \"hasn't even started destroying what's left\" CBS News"
    },
    {
      "title": "Iran war: One downed US fighter jet pilot rescued - DW.com",
      "source": "Google News Iran",
      "published_at": "2026-04-03 02:58:28",
      "summary": "Iran war: One downed US fighter jet pilot rescued DW.com"
    },
    {
      "title": "Control Over Strait of Hormuz Will Determine Who Wins the War - WSJ",
      "source": "Google News Iran",
      "published_at": "2026-04-03 01:00:00",
      "summary": "Control Over Strait of Hormuz Will Determine Who Wins the War WSJ"
    },
    {
      "title": "이란, '어린이 부대'까지 동원…지상전 대비 방어강화·징병확대",
      "source": "연합뉴스 국제",
      "published_at": "2026-04-03 18:06:54",
      "summary": "(뉴욕=연합뉴스) 김연숙 특파원 = 이란이 미국의 지상전에 대비해 주요 석유 항구의 방어를 강화하고 병력 확충에 나섰다고 미 일간 월스트리트저널..."
    }
  ]
}